{
    "base_files_url": "",
    "db_files": [],
    "db_id": "MiSTer_SAM_files",
    "db_url": "https://raw.githubusercontent.com/mrchrisster/MiSTer_SAM/main/MiSTer_SAMdb.json",
    "default_options": {},
    "files": {
	"Scripts/MiSTer_SAM_on.sh": {
	    "hash": "de60f71c856ca0b19974c0e84c080fa1",
	    "size": 118399,
	    "url": "https://raw.githubusercontent.com/mrchrisster/MiSTer_SAM/main/MiSTer_SAM_on.sh"
	}
    },
    "folders": {
	"Scripts": {}
    },
    "timestamp": 1675978580,
    "zips": {}
}
