{
    "base_files_url": "",
    "db_files": [],
    "db_id": "MiSTer_SAM_files",
    "db_url": "https://raw.githubusercontent.com/mrchrisster/MiSTer_SAM/main/MiSTer_SAMdb.json",
    "default_options": {},
    "files": {
	"Scripts/update_MiSTer_SAM.sh": {
	    "hash": "aecdaf3dfa53332660af4b59e4a6da60",
	    "size": 104586,
	    "url": "https://raw.githubusercontent.com/mrchrisster/MiSTer_SAM/main/MiSTer_SAM_on.sh"
	}
    },
    "folders": {
	"Scripts": {}
    },
    "timestamp": 1656025275,
    "zips": {}
}
