{

    "Atari_2600-_1982_ET_holiday_commercial.chd": {
        "title": "E.T.",
        "duration": 30
    },
    "ATARI_2600_aka_ATARI_2600_Jr_1986_TV_Commercial.chd": {
        "title": "Ms. Pac\\|Joust\\|Space Invaders\\|Pole\\|Solari\\|Midnight\\|H.E.R.O.",
        "duration": 31
    },
    "Atari_2600-_1983_Data_Age_Journey_Escape.chd": {
        "title": "Journey Escape",
        "duration": 31
    },
    "Atari_2600-_1983_Phoenix_Commercial.chd": {
        "title": "Phoenix",
        "duration": 31
    },
    "Atari_2600-_The_Fly_Theatrical_Commercial.chd": {
        "title": "Yars\\|Asteroids\\|Star Raiders",
        "duration": 121
    },
    "Atari_2600-_Vanguard_Commercial.chd": {
        "title": "Vanguard",
        "duration": 31
    },
    "Atari_2600-_Ms_Pac-Man_Commercial_1983.chd": {
        "title": "Ms. Pac-Man",
        "duration": 30
    },
    "Atari_2600-_ET_Christmas_1982.chd": {
        "title": "Extra-Terrestrial",
        "duration": 62
    },
    "Atari_2600-_Imagic_Atlantis_Commercial_1982.chd": {
        "title": "Atlantis",
        "duration": 31
    },
    "Atari_2600-_Mattel_Electronics_Tron_video_games_commercial.chd": {
        "title": "Deadly Discs\\|Adventures of",
        "duration": 31
    },
    "Atari_2600-_Pitfall_From_Activision_TV_Commercial.chd": {
        "title": "Pitfall",
        "duration": 31
    },
    "Atari_2600-_Super_Breakout_Video_Game_Ad_1982.chd": {
        "title": "Super Breakout",
        "duration": 34
    },
    "Atari_5200-_Jungle_Hunt__2600_1982_Commercial.chd": {
        "title": "Jungle Hunt",
        "duration": 30
    },
    "Atari_5200-_Joust__2600_commercial_1983.chd": {
        "title": "Joust",
        "duration": 31
    },
    "Atari_5200-_Star_Trek__2600_commercial_1983.chd": {
        "title": "Star Trek",
        "duration": 31
    },
    "Atari_5200-_Dig_Dug__2600_1983.chd": {
        "title": "Dig Dug",
        "duration": 31
    },
    "Atari_5200-_Mario_Bros_Game__2600_Commercial.chd": {
        "title": "Mario Bros",
        "duration": 31
    }
}